alara/__init__.py
alara/main.py
alara-0.3.3.dist-info/METADATA
alara-0.3.3.dist-info/WHEEL
alara-0.3.3.dist-info/entry_points.txt
alara-0.3.3.dist-info/top_level.txt
alara-0.3.3.dist-info/RECORD
